docs/conf.py
raddefects/__init__.py
raddefects/core.py
raddefects/analysis/transition_levels.py
raddefects/cli/__init__.py
raddefects/cli/main.py
raddefects/sxda/analysis.py
raddefects/sxda/io.py
raddefects-0.1.3.dist-info/LICENSE
raddefects-0.1.3.dist-info/METADATA
raddefects-0.1.3.dist-info/WHEEL
raddefects-0.1.3.dist-info/entry_points.txt
raddefects-0.1.3.dist-info/top_level.txt
raddefects-0.1.3.dist-info/RECORD
