Metadata-Version: 2.1
Name: raddefects
Version: 0.1.3
Summary: Framework to analyze properties of radiation-induced defects in semiconductor materials from first principles.
Author-email: Alexander Hauck <ash5615@psu.edu>
License: MIT License
Project-URL: Homepage, https://radDefects.readthedocs.io/en/latest/
Project-URL: Repository, https://github.com/hauck-as/radDefects
Classifier: Programming Language :: Python :: 3
Classifier: License :: OSI Approved :: MIT License
Classifier: Operating System :: OS Independent
Requires-Python: >=3.6
License-File: LICENSE
Requires-Dist: requests
Requires-Dist: numpy
Requires-Dist: pymatgen
Requires-Dist: mp-api
Requires-Dist: vise
Requires-Dist: pydefect
Requires-Dist: sumo
Requires-Dist: pymatgen-analysis-defects
Requires-Dist: niet
Requires-Dist: importlib-metadata ; python_version < "3.12"
